communications_protocol/__init__.py
communications_protocol/communications_protocol.py
communications_protocol/utils.py
communications_protocol-0.1.0.dist-info/METADATA
communications_protocol-0.1.0.dist-info/WHEEL
communications_protocol-0.1.0.dist-info/top_level.txt
communications_protocol-0.1.0.dist-info/RECORD
