Metadata-Version: 2.1
Name: communications-protocol
Version: 0.1.0
Summary: A package for communication protocol handling
Home-page: https://github.com/yourusername/yourproject
Author: lhb
Author-email: spike.edjet@gmail.com
License: UNKNOWN
Platform: UNKNOWN
Classifier: Programming Language :: Python :: 3
Classifier: License :: OSI Approved :: MIT License
Classifier: Operating System :: OS Independent
Requires-Python: >=3.6
Requires-Dist: PySide6
